{
  "project_info": {
    "project_number": "675460424491",
    "project_id": "netmeracrossplatforms",
    "storage_bucket": "netmeracrossplatforms.appspot.com"
  },
  "client": [
    {
      "client_info": {
        "mobilesdk_app_id": "1:675460424491:android:fb24000b2cd8e14b281b6e",
        "android_client_info": {
          "package_name": "com.netmera.unity.plugin"
        }
      },
      "oauth_client": [
        {
          "client_id": "675460424491-lauodsmmbocrss4es084dcq79lt953k0.apps.googleusercontent.com",
          "client_type": 3
        }
      ],
      "api_key": [
        {
          "current_key": "AIzaSyByWFgPVutnGL8TzowVMZrjDnb9WjPOsPw"
        }
      ],
      "services": {
        "appinvite_service": {
          "other_platform_oauth_client": [
            {
              "client_id": "675460424491-lauodsmmbocrss4es084dcq79lt953k0.apps.googleusercontent.com",
              "client_type": 3
            }
          ]
        }
      }
    }
  ],
  "configuration_version": "1"
}